<?xml version="1.0"?>
<?iotk version="1.2.0"?>
<?iotk file_version="1.0"?>
<?iotk binary="F"?>
<?iotk qe_syntax="F"?>
<Root>
  <IRREPS_INFO>
    <QPOINT_NUMBER type="integer" size="1">
1
    </QPOINT_NUMBER>
    <QPOINT_GROUP_RANK type="integer" size="1">
        48
    </QPOINT_GROUP_RANK>
    <MINUS_Q_SYM type="logical" size="1">
T
    </MINUS_Q_SYM>
    <NUMBER_IRR_REP type="integer" size="1">
         2
    </NUMBER_IRR_REP>
    <REPRESENTION.1>
      <NUMBER_OF_PERTURBATIONS type="integer" size="1">
         3
      </NUMBER_OF_PERTURBATIONS>
      <PERTURBATION.1>
        <SYMMETRY_TYPE_CODE type="integer" size="1">
         9
        </SYMMETRY_TYPE_CODE>
        <SYMMETRY_TYPE type="character" size="1" len="15">
T_1u G_15  G_4-
        </SYMMETRY_TYPE>
        <DISPLACEMENT_PATTERN type="complex" size="6">
 0.000000000000000E+000, 0.000000000000000E+000
 0.000000000000000E+000, 0.000000000000000E+000
 0.000000000000000E+000, 0.000000000000000E+000
-3.583449252630990E-001, 0.000000000000000E+000
-6.523583034346014E-001, 0.000000000000000E+000
 6.678454600265787E-001, 0.000000000000000E+000
        </DISPLACEMENT_PATTERN>
      </PERTURBATION.1>
      <PERTURBATION.2>
        <SYMMETRY_TYPE_CODE type="integer" size="1">
         9
        </SYMMETRY_TYPE_CODE>
        <SYMMETRY_TYPE type="character" size="1" len="15">
T_1u G_15  G_4-
        </SYMMETRY_TYPE>
        <DISPLACEMENT_PATTERN type="complex" size="6">
 0.000000000000000E+000, 0.000000000000000E+000
 0.000000000000000E+000, 0.000000000000000E+000
 0.000000000000000E+000, 0.000000000000000E+000
-7.605594918604954E-001, 0.000000000000000E+000
-2.108689230985668E-001, 0.000000000000000E+000
-6.140712960334133E-001, 0.000000000000000E+000
        </DISPLACEMENT_PATTERN>
      </PERTURBATION.2>
      <PERTURBATION.3>
        <SYMMETRY_TYPE_CODE type="integer" size="1">
         9
        </SYMMETRY_TYPE_CODE>
        <SYMMETRY_TYPE type="character" size="1" len="15">
T_1u G_15  G_4-
        </SYMMETRY_TYPE>
        <DISPLACEMENT_PATTERN type="complex" size="6">
 0.000000000000000E+000, 0.000000000000000E+000
 0.000000000000000E+000, 0.000000000000000E+000
 0.000000000000000E+000, 0.000000000000000E+000
-5.414223618203159E-001, 0.000000000000000E+000
 7.279855364024613E-001, 0.000000000000000E+000
 4.205934912831292E-001, 0.000000000000000E+000
        </DISPLACEMENT_PATTERN>
      </PERTURBATION.3>
    </REPRESENTION.1>
    <REPRESENTION.2>
      <NUMBER_OF_PERTURBATIONS type="integer" size="1">
         3
      </NUMBER_OF_PERTURBATIONS>
      <PERTURBATION.1>
        <SYMMETRY_TYPE_CODE type="integer" size="1">
         9
        </SYMMETRY_TYPE_CODE>
        <SYMMETRY_TYPE type="character" size="1" len="15">
T_1u G_15  G_4-
        </SYMMETRY_TYPE>
        <DISPLACEMENT_PATTERN type="complex" size="6">
-7.380020564081664E-001, 0.000000000000000E+000
 5.147821106253638E-001, 0.000000000000000E+000
 4.362938726562786E-001, 0.000000000000000E+000
 0.000000000000000E+000, 0.000000000000000E+000
 0.000000000000000E+000, 0.000000000000000E+000
 0.000000000000000E+000, 0.000000000000000E+000
        </DISPLACEMENT_PATTERN>
      </PERTURBATION.1>
      <PERTURBATION.2>
        <SYMMETRY_TYPE_CODE type="integer" size="1">
         9
        </SYMMETRY_TYPE_CODE>
        <SYMMETRY_TYPE type="character" size="1" len="15">
T_1u G_15  G_4-
        </SYMMETRY_TYPE>
        <DISPLACEMENT_PATTERN type="complex" size="6">
-4.449614749889836E-001, 0.000000000000000E+000
 1.148346684736833E-001, 0.000000000000000E+000
-8.881566780091040E-001, 0.000000000000000E+000
 0.000000000000000E+000, 0.000000000000000E+000
 0.000000000000000E+000, 0.000000000000000E+000
 0.000000000000000E+000, 0.000000000000000E+000
        </DISPLACEMENT_PATTERN>
      </PERTURBATION.2>
      <PERTURBATION.3>
        <SYMMETRY_TYPE_CODE type="integer" size="1">
         9
        </SYMMETRY_TYPE_CODE>
        <SYMMETRY_TYPE type="character" size="1" len="15">
T_1u G_15  G_4-
        </SYMMETRY_TYPE>
        <DISPLACEMENT_PATTERN type="complex" size="6">
-5.073088314951214E-001, 0.000000000000000E+000
-8.495954198891581E-001, 0.000000000000000E+000
 1.443099857612757E-001, 0.000000000000000E+000
 0.000000000000000E+000, 0.000000000000000E+000
 0.000000000000000E+000, 0.000000000000000E+000
 0.000000000000000E+000, 0.000000000000000E+000
        </DISPLACEMENT_PATTERN>
      </PERTURBATION.3>
    </REPRESENTION.2>
  </IRREPS_INFO>
</Root>
 
